jmake/__init__.py
jmake/generator.py
jmake/jmake.py
jmake/scriptenv.py
jmake/utils.py
jmake/builtin/__init__.py
jmake/builtin/vulkan.py
jmake-0.3.3.dist-info/LICENSE
jmake-0.3.3.dist-info/METADATA
jmake-0.3.3.dist-info/WHEEL
jmake-0.3.3.dist-info/top_level.txt
jmake-0.3.3.dist-info/RECORD
