Metadata-Version: 2.1
Name: jmake
Version: 0.3.3
Summary: C++ build system
License: Apache License
Project-URL: Homepage, https://github.com/DanDanCool/jmake
Requires-Python: >=3.10
License-File: LICENSE
Requires-Dist: jmllib
